KiwiRail_TMS_Checkdigit/__init__.py
KiwiRail_TMS_Checkdigit/tms_checkdigit.py
kiwirail_tms_checkdigit-1.1.0.dist-info/METADATA
kiwirail_tms_checkdigit-1.1.0.dist-info/WHEEL
kiwirail_tms_checkdigit-1.1.0.dist-info/licenses/LICENSE
kiwirail_tms_checkdigit-1.1.0.dist-info/RECORD
