Metadata-Version: 2.4
Name: KiwiRail-TMS-Checkdigit
Version: 1.1.0
Summary: A package for calculating the check digit of a TMS number
Project-URL: Documentation, https://github.com/cdfer/KiwiRail_TMS_Checkdigit_Python
Project-URL: Source, https://github.com/cdfer/KiwiRail_TMS_Checkdigit_Python
Author-email: Chris Dirks <cdirksfer@email.com>
License: Copyright 2024 Chris Dirks
License-File: LICENSE
Requires-Python: >=3.9
